clf_inference_intelcomp/__init__.py
clf_inference_intelcomp/classification.py
clf_inference_intelcomp/utils.py
clf_inference_intelcomp/data/classes.yaml
clf_inference_intelcomp/data/models.yaml
clf_inference_intelcomp-0.1.6.dist-info/LICENSE
clf_inference_intelcomp-0.1.6.dist-info/METADATA
clf_inference_intelcomp-0.1.6.dist-info/WHEEL
clf_inference_intelcomp-0.1.6.dist-info/top_level.txt
clf_inference_intelcomp-0.1.6.dist-info/RECORD
