Metadata-Version: 2.1
Name: clf-inference-intelcomp
Version: 0.1.6
Summary: Python package to perform inference using Intelcomp's hierarchical text classifiers.
Home-page: https://github.com/IntelCompH2020
Author: Marc Pàmies & Joan Llop
Author-email: langtech@bsc.es
License: MIT
Keywords: intelcomp,NLP,text classification,hierarchical classification,taxonomy learning
Platform: any
Classifier: Natural Language :: English
Classifier: Development Status :: 4 - Beta
Classifier: Intended Audience :: Science/Research
Classifier: License :: OSI Approved :: MIT License
Classifier: Operating System :: POSIX :: Linux
Classifier: Programming Language :: Python :: 3.7
Classifier: Programming Language :: Python :: 3.8
Classifier: Programming Language :: Python :: 3.9
Classifier: Topic :: Scientific/Engineering :: Artificial Intelligence
Requires-Dist: torch
Requires-Dist: xformers
Requires-Dist: transformers
